{
    "dono": "6000646692",
    "manutencao": "false",
    "userDono": "@zxyddy2",
    "versao": "2.1.1",
    "updateDAte": "18/02/2021 as 21:28",
    "price": {
        "Gold": 30,
        "standard": 10,
        "default": 5,
        "prepaid": 5,
        "gold": 30,
        "Default": 30
    },
    "pricemix": {
        "2": 10,
        "3": 50,
        "default": 15
    },
    "welcome": "Oi, {nome}",
    "valorpix": "Oi, {nome}",
    "text_maintain_mode": "Ops... Estamos em manutenção no momento.",
    "pix_message": "Transfira o valor da recarga para: \n\n PIX → lucas.silva.santos@gmail.com \n Nome → Lucas Silva Santos \n Banco → Mercadopago \n\n Comprovante → @ReiDosCartoesVT",
    "text_btn_cc_store": "🛍 Loja de CC's",
    "text_btn_add_funds": "💸 + Saldo",
    "text_btn_informations": "ℹ️ Informações",
    "text_store_1": "...bem-vindo a nossa loja de CC's",
    "text_store_2": "✅ Suas informações",
    "text_store_3": "👉 *Veja as opções abaixo*",
    "text_infos_1": "234",
    "text_infos_2": "234",
    "text_infos_3": "234",
    "text_infos_4": "234"
}